[
  {
    "path": "/*",
    "timings": [
      {
        "metric": "interactive",
        "budget": 5000,
        "tolerance": 1000
      },
      {
        "metric": "first-contentful-paint",
        "budget": 2500,
        "tolerance": 500
      },
      {
        "metric": "largest-contentful-paint",
        "budget": 4000,
        "tolerance": 1000
      }
    ],
    "resourceSizes": [
      {
        "resourceType": "script",
        "budget": 500
      },
      {
        "resourceType": "total",
        "budget": 1500
      },
      {
        "resourceType": "font",
        "budget": 200
      }
    ],
    "resourceCounts": [
      {
        "resourceType": "third-party",
        "budget": 15
      }
    ]
  }
]
